rabbit_logger/__init__.py
rabbit_logger/apm/__init__.py
rabbit_logger/apm/async_apm.py
rabbit_logger/apm/sync_apm.py
rabbit_logger/apm/udp_apm.py
rabbit_logger/logger/__init__.py
rabbit_logger/logger/async_handler.py
rabbit_logger/logger/base_handler.py
rabbit_logger/logger/sync_handler.py
rabbit_logger/logger/udp_handler.py
tests/__init__.py
rabbit_logger-1.0.0.dist-info/LICENSE
rabbit_logger-1.0.0.dist-info/METADATA
rabbit_logger-1.0.0.dist-info/WHEEL
rabbit_logger-1.0.0.dist-info/top_level.txt
rabbit_logger-1.0.0.dist-info/RECORD
