Metadata-Version: 2.1
Name: rabbit-logger
Version: 1.0.0
Summary: APM and logging library with RabbitMQ integration
Home-page: https://github.com/single-service/rabbit-logger.git
Author: Aleksey
Author-email: your.email@example.com
License: MIT
Classifier: Programming Language :: Python :: 3
Classifier: License :: OSI Approved :: MIT License
Classifier: Operating System :: OS Independent
Requires-Python: >=3.7
License-File: LICENSE
Requires-Dist: typing_extensions
Requires-Dist: pika
Requires-Dist: psutil
Requires-Dist: aio_pika
